CHANGELOG.md
README.md
gungus/__init__.py
gungus-0.0.0.dist-info/METADATA
gungus-0.0.0.dist-info/WHEEL
gungus-0.0.0.dist-info/LICENSE.md
gungus-0.0.0.dist-info/RECORD
