Metadata-Version: 2.1
Name: gungus
Version: 0.0.0
Summary: 
Home-page: https://github.com/ttyrho/gungus
License: GPL-3.0-or-later
Author: Cesar Perez
Author-email: ttyrho@gmail.com
Maintainer: Cesar Perez
Maintainer-email: ttyrho@gmail.com
Requires-Python: >=3.9,<4.0
Classifier: Development Status :: 1 - Planning
Classifier: Intended Audience :: Science/Research
Classifier: License :: OSI Approved :: GNU General Public License v3 or later (GPLv3+)
Classifier: Programming Language :: Python :: 3
Classifier: Programming Language :: Python :: 3.9
Classifier: Programming Language :: Python :: 3.10
Classifier: Programming Language :: Python :: 3.11
Classifier: Topic :: Scientific/Engineering :: Artificial Intelligence
Project-URL: Repository, https://github.com/ttyrho/gungus
